Metadata-Version: 1.1
Name: mathoperation
Version: 0.1
Summary: Testing installation of Package
Home-page: https://github.com/SmithaSPrem/mathoperation
Author: Smitha
Author-email: UNKNOWN
License: UNKNOWN
Download-URL: https://github.com/SmithaSPrem/mathoperation/archive/refs/tags/v_0.1.tar.gz
Platform: UNKNOWN
